Workbook

Sheet Dashboard
B2: Cybersecurity Risk Register Dashboard
B4: Total Risks | D4: Average Score | F4: Open Risks | K4: Severity | L4: Count | N4: NIST Function | O4: Count | R4: Control Tests | S4: Count
B5: =COUNTA(Risk_Register!A2:A100) | D5: =IFERROR(AVERAGE(Risk_Register!P2:P100), 0) | F5: =COUNTIF(Risk_Register!M:M, "Open") | K5: Critical | L5: =COUNTIF(Risk_Register!Q:Q, "Critical") | N5: Identify | O5: =COUNTIF(Risk_Register!C:C, "Identify") | R5: Total Tests | S5: =COUNTA(Control_Testing_Log!A2:A100)
K6: High | L6: =COUNTIF(Risk_Register!Q:Q, "High") | N6: Protect | O6: =COUNTIF(Risk_Register!C:C, "Protect") | R6: Effective | S6: =COUNTIF(Control_Testing_Log!K:K, "Effective")
K7: Medium | L7: =COUNTIF(Risk_Register!Q:Q, "Medium") | N7: Detect | O7: =COUNTIF(Risk_Register!C:C, "Detect") | R7: Partially Effective / Exception | S7: =COUNTIF(Control_Testing_Log!K:K, "*Effective*")-COUNTIF(Control_Testing_Log!K:K, "Effective")
K8: Low | L8: =COUNTIF(Risk_Register!Q:Q, "Low") | N8: Respond | O8: =COUNTIF(Risk_Register!C:C, "Respond") | R8: Ineffective | S8: =COUNTIF(Control_Testing_Log!K:K, "Ineffective")
N9: Recover | O9: =COUNTIF(Risk_Register!C:C, "Recover")
N10: Govern | O10: =COUNTIF(Risk_Register!C:C, "Govern")

Sheet Risk_Register
A1: Risk ID | B1: Domain | C1: NIST Function | D1: Risk Title | E1: Cause | F1: Event | G1: Business Impact | H1: Existing Controls | I1: Control Gaps | J1: Mitigation Plan | K1: Owner | L1: Due Date | M1: Status | N1: Likelihood (1-5) | O1: Impact (1-5) | P1: Score | Q1: Rating
A2: R-001 | B2: Third-Party Risk | C2: Identify | D2: Vendor Data Exposure | E2: Unpatched 3rd-party file transfer software | F2: Unauthorized data exfiltration | G2: 2.8M employee records leaked | H2: Standard contracts | I2: No continuous patch monitoring | J2: Implement continuous vendor security audits | K2: Vendor Risk | L2: 2026-08-01 | M2: Open | N2: 4 | O2: 5 | P2: =N2*O2 | Q2: =IF(P2>=15, "Critical", IF(P2>=10, "High", IF(P2>=5, "Medium", "Low")))
A3: R-002 | B3: Cloud Security | C3: Protect | D3: Compromised CI/CD Pipeline | E3: Upstream compromise in developer tool | F3: Stolen AWS API keys | G3: Unauthorized access to core AWS infrastructure | H3: Static access keys | I3: Over-privileged keys, no behavioral monitoring | J3: Rotate keys, enforce least privilege via AWS SCPs | K3: Cloud Sec | L3: 2026-07-15 | M3: In Progress | N3: 4 | O3: 4 | P3: =N3*O3 | Q3: =IF(P3>=15, "Critical", IF(P3>=10, "High", IF(P3>=5, "Medium", "Low")))
A4: R-003 | B4: Identity & Access | C4: Detect | D4: Hijacked Network Edge Devices | E4: Misconfigured customer routers on AWS | F4: State-sponsored credential harvesting | G4: Credential replay attacks disrupting logistics | H4: Basic firewalls | I4: No edge device auditing or replay detection | J4: Monthly edge audits, enable replay alerts | K4: Network Sec | L4: 2026-07-30 | M4: Open | N4: 3 | O4: 5 | P4: =N4*O4 | Q4: =IF(P4>=15, "Critical", IF(P4>=10, "High", IF(P4>=5, "Medium", "Low")))
A5: R-004 | B5: Endpoint Security | C5: Protect | D5: Malicious Code in Open-Source | E5: Implicit trust in open-source packages | F5: Poisoned packages infect developer laptops | G5: Malicious code bypasses endpoint security | H5: Standard antivirus | I5: No hardware MFA, unvetted software allowed | J5: Enforce hardware MFA, implement software allowlist | K5: AppSec | L5: 2026-08-15 | M5: Open | N5: 4 | O5: 3 | P5: =N5*O5 | Q5: =IF(P5>=15, "Critical", IF(P5>=10, "High", IF(P5>=5, "Medium", "Low")))
A6: R-005 | B6: Third-Party Risk | C6: Recover | D6: Logistics Partner Ransomware | E6: Phishing attack on regional delivery partner | F6: Ransomware encrypts dispatch systems | G6: Regional delivery halts for 48 hours | H6: Email filtering | I6: Lack of mandated offline backups for vendors | J6: Require immutable backups in vendor contracts | K6: Vendor Risk | L6: 2026-09-01 | M6: Open | N6: 3 | O6: 4 | P6: =N6*O6 | Q6: =IF(P6>=15, "Critical", IF(P6>=10, "High", IF(P6>=5, "Medium", "Low")))
A7: R-006 | B7: Cloud Security | C7: Protect | D7: S3 Bucket Misconfiguration | E7: Human error during infrastructure deployment | F7: Public exposure of internal shipping manifests | G7: Competitors access proprietary routing data | H7: Manual cloud reviews | I7: No automated posture management (CSPM) | J7: Deploy CSPM tools to block public S3 buckets | K7: Cloud Sec | L7: 2026-07-20 | M7: Closed | N7: 2 | O7: 4 | P7: =N7*O7 | Q7: =IF(P7>=15, "Critical", IF(P7>=10, "High", IF(P7>=5, "Medium", "Low")))
A8: R-007 | B8: Logging & Monitoring | C8: Detect | D8: Lack of API Traffic Visibility | E8: Undocumented shadow APIs used by mobile app | F8: Data scraping of product inventory | G8: Competitor price manipulation | H8: Web Application Firewall | I8: No dedicated API discovery and monitoring | J8: Implement API gateway with strict rate limiting | K8: AppSec | L8: 2026-08-10 | M8: In Progress | N8: 4 | O8: 3 | P8: =N8*O8 | Q8: =IF(P8>=15, "Critical", IF(P8>=10, "High", IF(P8>=5, "Medium", "Low")))
A9: R-008 | B9: Third-Party Risk | C9: Identify | D9: Overprivileged Cloud Admins (EU) | E9: Role creep over several years | F9: Insider threat or hijacked admin account | G9: Complete deletion of cloud storage buckets | H9: Annual access reviews | I9: Too much standing privilege, no Just-in-Time access | J9: Implement Just-in-Time (JIT) cloud access | K9: Cloud Sec | L9: 2026-11-01 | M9: Open | N9: 4 | O9: 4 | P9: =N9*O9 | Q9: =IF(P9>=15, "Critical", IF(P9>=10, "High", IF(P9>=5, "Medium", "Low")))
A10: R-009 | B10: Backup & Recovery | C10: Recover | D10: Insecure API on Mobile Delivery App (APAC) | E10: Rushed development cycle | F10: Driver route data scraped by competitors | G10: Loss of competitive advantage and privacy violation | H10: App store security reviews | I10: No API rate limiting or authentication checks | J10: Audit all mobile APIs and implement rate limiting | K10: AppSec | L10: 2026-09-24 | M10: Open | N10: 3 | O10: 3 | P10: =N10*O10 | Q10: =IF(P10>=15, "Critical", IF(P10>=10, "High", IF(P10>=5, "Medium", "Low")))
A11: R-010 | B11: Backup & Recovery | C11: Recover | D11: Missing Endpoint EDR on Contractor Laptops (NA) | E11: BYOD policy for seasonal warehouse contractors | F11: Contractor laptop introduces malware | G11: Local network infection | H11: Basic antivirus | I11: No advanced threat hunting or EDR | J11: Require virtual desktop (VDI) for all BYOD contractors | K11: Endpoint Sec | L11: 2026-08-24 | M11: In Progress | N11: 4 | O11: 4 | P11: =N11*O11 | Q11: =IF(P11>=15, "Critical", IF(P11>=10, "High", IF(P11>=5, "Medium", "Low")))
A12: R-011 | B12: Backup & Recovery | C12: Recover | D12: Overprivileged Cloud Admins (Global) | E12: Role creep over several years | F12: Insider threat or hijacked admin account | G12: Complete deletion of cloud storage buckets | H12: Annual access reviews | I12: Too much standing privilege, no Just-in-Time access | J12: Implement Just-in-Time (JIT) cloud access | K12: Cloud Sec | L12: 2026-08-20 | M12: Open | N12: 5 | O12: 4 | P12: =N12*O12 | Q12: =IF(P12>=15, "Critical", IF(P12>=10, "High", IF(P12>=5, "Medium", "Low")))
A13: R-012 | B13: Vulnerability Management | C13: Identify | D13: Missing Endpoint EDR on Contractor Laptops (APAC) | E13: BYOD policy for seasonal warehouse contractors | F13: Contractor laptop introduces malware | G13: Local network infection | H13: Basic antivirus | I13: No advanced threat hunting or EDR | J13: Require virtual desktop (VDI) for all BYOD contractors | K13: Endpoint Sec | L13: 2026-08-28 | M13: In Progress | N13: 3 | O13: 1 | P13: =N13*O13 | Q13: =IF(P13>=15, "Critical", IF(P13>=10, "High", IF(P13>=5, "Medium", "Low")))
... A59: GV-008 | B59: Governance & Oversight | C59: Govern | D59: No Documented Cybersecurity Risk RACI | E59: Roles for cybersecurity risk management not documented (no RACI) across supply chain, IT, and warehouse ops | F59: During a cross-functional incident, teams are unclear who owns investigation, containment, reporting | G59: Slower containment, unclear accountability during audits, repeat findings | H59: Informal team ownership by department | I59: No documented RACI matrix across supply chain, IT, and warehouse operations | J59: Publish a RACI matrix defining ownership for investigation, containment, and reporting across all functions | K59: GRC/Compliance | L59: 2026-10-15 | M59: Open | N59: 3 | O59: 3 | P59: =N59*O59 | Q59: =IF(P59>=15, "Critical", IF(P59>=10, "High", IF(P59>=5, "Medium", "Low")))

Sheet Control_Testing_Log
A1: Test ID | B1: Related Risk ID(s) | C1: Control Name | D1: Control Owner | E1: NIST CSF Function | F1: Test Objective | G1: Test Procedure Performed | H1: Evidence Reviewed | I1: Sample Size | J1: Test Date | K1: Result | L1: Finding / Exception | M1: Recommended Remediation | N1: Tester
A2: CT-001 | B2: R-008, R-011, R-022, R-029, R-034, R-038, R-044, R-050 | C2: Annual Access Reviews (Cloud Admin Privileged Access) | D2: Cloud Sec | E2: Identify / Protect | F2: Verify privileged cloud admin access is reviewed at least annually and access no longer required is revoked timely. | G2: Selected a sample of 15 privileged cloud admin accounts across NA, EU, APAC, and LATAM from the most recent access-review cycle. Confirmed each had a documented sign-off within 12 months, and traced 5 'access revoked' decisions to confirm actual deprovisioning within 5 business days. | H2: Access review sign-off log (Q2 2026), IAM deprovisioning audit trail, sample account list. | I2: 15 of ~140 privileged accounts | J2: 2026-08-15 | K2: Partially Effective | L2: 3 of 15 sampled accounts (20%) had review sign-offs completed but access was not revoked in the IAM system for 12-19 days after the 'revoke' decision, exceeding the 5-business-day SLA. Root cause: manual deprovisioning process with no system-enforced deadline. | M2: Implement automated deprovisioning triggered directly by access-review decisions rather than a manual follow-up ticket. | N2: A. Rehman
A3: CT-002 | B3: R-014, R-037, R-041, R-043, R-045, R-048, R-049 | C3: Warehouse IoT Network Segmentation | D3: OT Security | E3: Protect / Detect | F3: Verify warehouse IoT devices (barcode scanners, sortation sensors) are logically segmented from the corporate network. | G3: Reviewed network architecture diagrams for 3 warehouse sites (NA, EU, APAC). Reviewed firewall/VLAN configuration exports confirming IoT VLAN isolation, and checked for exception/bridge rules allowing IoT-to-corporate traffic. | H3: Network architecture diagrams, firewall rule exports, VLAN configuration records. | I3: 3 of 22 warehouse sites | J3: 2026-08-18 | K3: Effective (1 exception) | L3: 2 of 3 sites had clean segmentation with no cross-VLAN exceptions. 1 site (APAC) had a temporary firewall rule opened for a vendor maintenance visit 4 months prior that was never closed, allowing IoT VLAN traffic to reach a corporate file share. | M3: Implement a firewall exception expiration/auto-review process for all vendor-maintenance-related temporary rules. | N3: A. Rehman
A4: CT-003 | B4: R-018, R-023, R-030, R-032 | C4: HR Portal Authentication Controls | D4: Identity Team | E4: Protect | F4: Determine whether password complexity rules are sufficient to mitigate unauthorized access in the continued absence of MFA. | G4: Reviewed HR portal authentication configuration and password policy settings. Checked whether elevated-access HR admin accounts had MFA enforced despite the general population not having it. Reviewed 90 days of failed-login/lockout logs for credential-stuffing indicators. | H4: Authentication configuration export, password policy documentation, 90-day failed-login log. | I4: Full population, 90-day window | J4: 2026-08-20 | K4: Ineffective | L4: Password complexity alone does not constitute an adequate compensating control for the absence of MFA on a system handling PII (per NIST 800-63B). Failed-login logs showed 340 failed attempts across 22 accounts in 90 days, consistent with credential-stuffing patterns, with no automated lockout until the 10th consecutive failure. | M4: Prioritize MFA enforcement on the HR portal as a Critical remediation item (tracked as R-018/023/030/032); reduce lockout threshold to 5 attempts in the interim. | N4: A. Rehman
A5: CT-004 | B5: R-015, R-020, R-021, R-042 | C5: Third-Party Vendor Remote Access (VPN) | D5: Vendor Risk | E5: Protect | F5: Verify third-party HVAC/facilities vendors are restricted to least-privilege VPN access and deprovisioned when contracts end. | G5: Selected a sample of 8 active third-party vendor VPN accounts. Confirmed each was tied to an active, unexpired vendor contract, and verified VPN access scope was restricted to building-management-system IP ranges only. | H5: Vendor contract register, VPN access-grant list, network access-scope configuration. | I5: 8 of 19 active third-party VPN accounts | J5: 2026-08-21 | K5: Effective | L5: All 8 sampled accounts were correctly scoped and tied to active contracts. No exceptions noted. | M5: None required; expand sample size in the next testing cycle given population size. | N5: A. Rehman
A6: CT-005 | B6: R-019, R-024, R-033 | C6: Regional Backup & Recovery Testing | D6: Disaster Recovery | E6: Recover | F6: Verify weekly cloud backups for APAC regional systems can be successfully restored within the recovery time objective (RTO). | G6: Confirmed backup job completion logs for the last 8 weekly cycles. Requested evidence of the most recent backup restoration test for the APAC region. | H6: Backup job completion logs (8-week window), disaster recovery test records. | I6: 8 of 8 backup cycles; 1 restoration test record requested | J6: 2026-08-22 | K6: Ineffective | L6: All 8 weekly backup jobs completed successfully, but no backup restoration test has been performed for the APAC region in over 18 months. Backup existence was confirmed; recoverability was not. | M6: Schedule and execute a full restoration test for the APAC region within 30 days; establish a semi-annual restoration-testing cadence for all regions. | N6: A. Rehman
